gpumon/__init__.py
gpumon/gpumon.old.py
gpumon/gpumon.py
gpumon-0.0.11.dist-info/METADATA
gpumon-0.0.11.dist-info/WHEEL
gpumon-0.0.11.dist-info/entry_points.txt
gpumon-0.0.11.dist-info/top_level.txt
gpumon-0.0.11.dist-info/RECORD
