Metadata-Version: 2.1
Name: gpumon
Version: 0.0.11
Summary: A simple GPU monitoring tool.
Home-page: https://github.com/abdkhanstd/GpuMonitor
Author: ABD
Author-email: abdkhan@163.com
License: MIT
Classifier: Programming Language :: Python :: 3
Classifier: License :: OSI Approved :: MIT License
Classifier: Operating System :: OS Independent
Requires-Python: >=3.6
Requires-Dist: psutil
Requires-Dist: gputil
